aipype_g/__init__.py
aipype_g/py.typed
aipype_g/tasklib/__init__.py
aipype_g/tasklib/gmail_list_emails_task.py
aipype_g/tasklib/gmail_models.py
aipype_g/tasklib/gmail_read_email_task.py
aipype_g/tasklib/gmail_service.py
aipype_g/tasklib/google_auth_service.py
aipype_g/tasklib/google_oauth_task.py
aipype_g/tasklib/google_sheets_models.py
aipype_g/tasklib/google_sheets_service.py
aipype_g/tasklib/read_google_sheet_task.py
aipype_g-0.1.0a5.dist-info/METADATA
aipype_g-0.1.0a5.dist-info/WHEEL
aipype_g-0.1.0a5.dist-info/RECORD
