Metadata-Version: 2.4
Name: aipype-g
Version: 0.1.0a5
Summary: Google API integrations for the aipype framework
Project-URL: Homepage, https://github.com/mobisoftinfotech/aipype
Project-URL: Repository, https://github.com/mobisoftinfotech/aipype
Project-URL: Issues, https://github.com/mobisoftinfotech/aipype/issues
Author-email: Pritam Barhate <pritambarhate@mobisoftinfotech.com>
Keywords: agents,ai,gmail,google,sheets,tasklib
Classifier: Development Status :: 3 - Alpha
Classifier: Intended Audience :: Developers
Classifier: License :: OSI Approved :: MIT License
Classifier: Operating System :: OS Independent
Classifier: Programming Language :: Python :: 3
Classifier: Programming Language :: Python :: 3.12
Classifier: Topic :: Scientific/Engineering :: Artificial Intelligence
Requires-Python: >=3.12
Requires-Dist: aipype>=0.1.0a1
Requires-Dist: google-api-python-client>=2.0.0
Requires-Dist: google-auth-oauthlib>=1.0.0
Requires-Dist: google-auth>=2.0.0
